{"viewers":[{"id":0,"username":"penguinsavage16","karma":600,"coins":39137},{"id":1,"username":"k1ll4nt","karma":10,"coins":117425},{"id":2,"username":"sharkinstv","karma":600,"coins":101124},{"id":3,"username":"olirules10","karma":100,"coins":5620},{"id":4,"username":"jaeger972","karma":96,"coins":2150},{"id":5,"username":"glowrasx","karma":600,"coins":4639},{"id":6,"username":"sebbeke","karma":600,"coins":10103},{"id":7,"username":"nightbot","karma":100,"coins":183140},{"id":8,"username":"beerspam","karma":600,"coins":19221},{"id":9,"username":"irrigatio","karma":600,"coins":31685},{"id":10,"username":"streamlabs","karma":100,"coins":152930},{"id":11,"username":"icewizerds","karma":100,"coins":123650},{"id":12,"username":"modog0","karma":600,"coins":182085},{"id":13,"username":"soundalerts","karma":100,"coins":123650},{"id":14,"username":"spionneke","karma":100,"coins":128407},{"id":15,"username":"sathrek","karma":100,"coins":44252},{"id":16,"username":"abbottcostello","karma":100,"coins":123650},{"id":17,"username":"carbon14xyz","karma":100,"coins":123650},{"id":18,"username":"jointeffortt","karma":100,"coins":122650},{"id":19,"username":"slmlshadowwing","karma":600,"coins":3442},{"id":20,"username":"commanderroot","karma":100,"coins":122150},{"id":21,"username":"jared22","karma":490,"coins":157655},{"id":22,"username":"togliy96","karma":100,"coins":3910},{"id":23,"username":"sillygnome225","karma":100,"coins":150},{"id":24,"username":"vulpertinger","karma":100,"coins":150},{"id":25,"username":"bigbadbill_87","karma":100,"coins":150},{"id":26,"username":"unicandy","karma":600,"coins":40991},{"id":27,"username":"tygrysgra","karma":447,"coins":115685},{"id":28,"username":"stargirlgames","karma":100,"coins":2590},{"id":29,"username":"vonreder","karma":100,"coins":150},{"id":30,"username":"sgwis","karma":140,"coins":83790},{"id":31,"username":"cosmichunter89","karma":600,"coins":26115},{"id":32,"username":"bingcortana","karma":100,"coins":81150},{"id":33,"username":"charmedwings202","karma":140,"coins":3118},{"id":34,"username":"virgoproz","karma":100,"coins":81150},{"id":35,"username":"tawmtawmz","karma":100,"coins":81150},{"id":36,"username":"v_and_k","karma":100,"coins":81150},{"id":37,"username":"ildelara","karma":100,"coins":81150},{"id":38,"username":"communityshowcase","karma":100,"coins":150},{"id":39,"username":"wow_yenki_with_no_brim","karma":100,"coins":87740},{"id":40,"username":"ehrabz","karma":100,"coins":150},{"id":41,"username":"acidicooze","karma":100,"coins":150},{"id":42,"username":"minecraft_1124","karma":132,"coins":2173},{"id":43,"username":"log657","karma":100,"coins":150},{"id":44,"username":"polandspaceprogram","karma":100,"coins":84990},{"id":45,"username":"adamaidreemur","karma":138,"coins":25270},{"id":46,"username":"extramoar","karma":100,"coins":80150},{"id":47,"username":"miniature_minotaur","karma":600,"coins":13643},{"id":48,"username":"dragonboy_1","karma":100,"coins":1430},{"id":49,"username":"bloodlustr","karma":100,"coins":150},{"id":50,"username":"mararomano","karma":100,"coins":150},{"id":51,"username":"dragonmagic85","karma":100,"coins":80150},{"id":52,"username":"sir_psycho_aussie","karma":168,"coins":3554},{"id":53,"username":"svrem125","karma":378,"coins":5546},{"id":54,"username":"robert_snype","karma":600,"coins":96033},{"id":55,"username":"ssj2240","karma":100,"coins":150},{"id":56,"username":"almightyherokiller","karma":100,"coins":1430},{"id":57,"username":"shmookle","karma":600,"coins":16190},{"id":58,"username":"cabecoupecou","karma":100,"coins":150},{"id":59,"username":"snorklefork","karma":100,"coins":150},{"id":60,"username":"normabram","karma":100,"coins":80150},{"id":61,"username":"zamioku","karma":100,"coins":150},{"id":62,"username":"kormok","karma":600,"coins":13541},{"id":63,"username":"havethis2","karma":100,"coins":80150},{"id":64,"username":"judi100","karma":600,"coins":7047},{"id":65,"username":"charlytaunic0rn","karma":100,"coins":1430},{"id":66,"username":"fuzzybeanplays","karma":100,"coins":82912},{"id":67,"username":"bluebilliejean","karma":100,"coins":80150},{"id":68,"username":"duckwit1","karma":100,"coins":80150},{"id":69,"username":"effortlessanxiety","karma":100,"coins":150},{"id":70,"username":"loyalshadusk","karma":100,"coins":80150},{"id":71,"username":"plaguedoctor53","karma":600,"coins":17827},{"id":72,"username":"vinnysc10","karma":100,"coins":150},{"id":73,"username":"stewlew89","karma":100,"coins":150},{"id":74,"username":"bunnymama66","karma":100,"coins":82815},{"id":75,"username":"devinisdreamy","karma":100,"coins":81840},{"id":76,"username":"the_heye","karma":100,"coins":150},{"id":77,"username":"mashingduck","karma":100,"coins":2835},{"id":78,"username":"lonelyfighter","karma":100,"coins":150},{"id":79,"username":"picard65","karma":110,"coins":2988},{"id":80,"username":"ftopayr","karma":100,"coins":150},{"id":81,"username":"iviotic","karma":100,"coins":150},{"id":82,"username":"doctorrex90","karma":100,"coins":150},{"id":83,"username":"electricallongboard","karma":100,"coins":150},{"id":84,"username":"theoneandonlylee","karma":100,"coins":150},{"id":85,"username":"relevantgoat","karma":100,"coins":150},{"id":86,"username":"mrbrewed","karma":100,"coins":150},{"id":87,"username":"ahoulton","karma":100,"coins":150},{"id":88,"username":"thegodsrag","karma":100,"coins":4730},{"id":89,"username":"jba14","karma":100,"coins":500},{"id":90,"username":"xxdarcksolxx","karma":100,"coins":500},{"id":91,"username":"mckitch3n","karma":100,"coins":500},{"id":92,"username":"aten","karma":100,"coins":500},{"id":93,"username":"im12watisdis","karma":100,"coins":500},{"id":94,"username":"rubenruben44","karma":600,"coins":1958},{"id":95,"username":"karth_42","karma":100,"coins":500},{"id":96,"username":"casinothanks","karma":100,"coins":500},{"id":97,"username":"garlyck123","karma":254,"coins":14912},{"id":98,"username":"australian_cub","karma":456,"coins":7582},{"id":99,"username":"wpfid5555","karma":100,"coins":500},{"id":100,"username":"buriasgaming","karma":100,"coins":500},{"id":101,"username":"mrfun01","karma":100,"coins":4950},{"id":102,"username":"mr_sand_man537","karma":100,"coins":1670},{"id":103,"username":"gpc_diamondars22","karma":100,"coins":500},{"id":104,"username":"gardy_94","karma":293,"coins":7720},{"id":105,"username":"baddhist","karma":330,"coins":6083},{"id":106,"username":"buhci0","karma":213,"coins":2960},{"id":107,"username":"juancabardo","karma":100,"coins":500},{"id":108,"username":"ruurra","karma":100,"coins":500},{"id":109,"username":"justboti1","karma":600,"coins":7983},{"id":110,"username":"skyrish27","karma":100,"coins":500},{"id":111,"username":"droopdoggg","karma":100,"coins":500},{"id":112,"username":"vexingraven","karma":177,"coins":4974},{"id":113,"username":"amindsescape","karma":416,"coins":3534},{"id":114,"username":"stegos063","karma":100,"coins":500},{"id":115,"username":"gowithhim","karma":100,"coins":500},{"id":116,"username":"cheese_bird","karma":383,"coins":4167},{"id":117,"username":"syralak","karma":100,"coins":500},{"id":118,"username":"themudmasher","karma":100,"coins":500},{"id":119,"username":"thesampowi","karma":100,"coins":500},{"id":120,"username":"incrediibill","karma":100,"coins":500},{"id":121,"username":"flobba_job","karma":100,"coins":500},{"id":122,"username":"leosmellmire","karma":278,"coins":1206},{"id":123,"username":"shadowdog6","karma":100,"coins":500},{"id":124,"username":"sudden_panda","karma":600,"coins":1396},{"id":125,"username":"gamingpanda6996","karma":600,"coins":1785},{"id":126,"username":"nebuyitra","karma":600,"coins":40110},{"id":127,"username":"noobsoupthesoupking","karma":160,"coins":10124},{"id":128,"username":"koeieuier","karma":600,"coins":17628},{"id":129,"username":"rmigui","karma":164,"coins":4426},{"id":130,"username":"rubberslayer","karma":100,"coins":500},{"id":131,"username":"refundthesky","karma":600,"coins":8660},{"id":132,"username":"arulive","karma":100,"coins":2120},{"id":133,"username":"aviedya","karma":100,"coins":2390},{"id":134,"username":"goldendragon900","karma":100,"coins":500},{"id":135,"username":"mmshaun23202","karma":100,"coins":1850},{"id":136,"username":"camdenkilby","karma":100,"coins":500},{"id":137,"username":"maddyson_moy_bog","karma":100,"coins":500},{"id":138,"username":"oasis_god","karma":100,"coins":500},{"id":139,"username":"heirmanttinan","karma":100,"coins":500},{"id":140,"username":"kishintern","karma":100,"coins":500},{"id":141,"username":"toadieypq","karma":100,"coins":500},{"id":142,"username":"conuput","karma":100,"coins":1850},{"id":143,"username":"snowmarkphoenix","karma":600,"coins":9653},{"id":144,"username":"ytinterweb1270","karma":100,"coins":1940},{"id":145,"username":"natonatural","karma":100,"coins":500},{"id":146,"username":"nahhhhhhhhhhhhhhhhhhg","karma":600,"coins":13327},{"id":147,"username":"soupkingtw","karma":198,"coins":4724},{"id":148,"username":"omegajeppe","karma":100,"coins":500},{"id":149,"username":"rverite","karma":100,"coins":3290},{"id":150,"username":"brrainz","karma":100,"coins":6385},{"id":151,"username":"smitingmurloc","karma":600,"coins":9450},{"id":152,"username":"icaro12oliveira","karma":100,"coins":500},{"id":153,"username":"kingc3530","karma":100,"coins":500},{"id":154,"username":"shinotama","karma":100,"coins":1850},{"id":155,"username":"grapedactyl","karma":100,"coins":1940},{"id":156,"username":"bluejay3657","karma":100,"coins":1850},{"id":157,"username":"frankdaghoul","karma":100,"coins":500},{"id":158,"username":"thecrispycrumpets","karma":177,"coins":7720},{"id":159,"username":"radbest","karma":100,"coins":2210},{"id":160,"username":"darkguld","karma":100,"coins":500},{"id":161,"username":"pokegamer69","karma":100,"coins":500},{"id":162,"username":"orionarquilian","karma":100,"coins":500},{"id":163,"username":"tex4prez","karma":100,"coins":680},{"id":164,"username":"rafflevantri","karma":100,"coins":500},{"id":165,"username":"zigulisegra","karma":100,"coins":500},{"id":166,"username":"captainskrew","karma":100,"coins":500},{"id":167,"username":"hunky_quark","karma":100,"coins":500},{"id":168,"username":"chutzy420","karma":600,"coins":2315},{"id":169,"username":"nik_92","karma":600,"coins":12280},{"id":170,"username":"ingamegf","karma":100,"coins":500},{"id":171,"username":"grabberreturns","karma":100,"coins":500},{"id":172,"username":"bang102","karma":100,"coins":500},{"id":173,"username":"caniisu","karma":100,"coins":1940},{"id":174,"username":"ciaran_is_awesome","karma":100,"coins":2120},{"id":175,"username":"acidkiss","karma":100,"coins":500},{"id":176,"username":"cilivarus","karma":100,"coins":500},{"id":177,"username":"crustyplunger","karma":100,"coins":500},{"id":178,"username":"violets_tv","karma":100,"coins":500}],"total":179}